aptly_ctl/Config.py
aptly_ctl/__init__.py
aptly_ctl/__main__.py
aptly_ctl/application.py
aptly_ctl/exceptions.py
aptly_ctl/subcommands/__init__.py
aptly_ctl/subcommands/copy.py
aptly_ctl/subcommands/publish.py
aptly_ctl/subcommands/put.py
aptly_ctl/subcommands/remove.py
aptly_ctl/subcommands/repo.py
aptly_ctl/subcommands/search.py
aptly_ctl/utils/ExtendedAptlyClient.py
aptly_ctl/utils/PackageFile.py
aptly_ctl/utils/PackageRef.py
aptly_ctl/utils/PubSpec.py
aptly_ctl/utils/Version.py
aptly_ctl/utils/__init__.py
aptly_ctl/utils/misc.py
aptly_ctl-0.10.dist-info/LICENSE
aptly_ctl-0.10.dist-info/METADATA
aptly_ctl-0.10.dist-info/WHEEL
aptly_ctl-0.10.dist-info/entry_points.txt
aptly_ctl-0.10.dist-info/top_level.txt
aptly_ctl-0.10.dist-info/RECORD
