Metadata-Version: 2.1
Name: aptly-ctl
Version: 0.10
Summary: Convenient command line Aptly API client
Home-page: https://github.com/cyril-s/aptly-ctl
Author: Kirill Shestakov
Author-email: freyr.sh@gmail.com
License: MIT
Platform: UNKNOWN
Classifier: Development Status :: 3 - Alpha
Classifier: Programming Language :: Python :: 3 :: Only
Classifier: Environment :: Console
Classifier: License :: OSI Approved :: MIT License
Requires-Python: >=3
Requires-Dist: aptly-api-client (<=0.2.1)
Requires-Dist: PyYAML
Requires-Dist: requests
Requires-Dist: fnvhash
